neuroslice/__init__.py
neuroslice/cli.py
neuroslice/core.py
neuroslice/utils.py
neuroslice-1.0.4.dist-info/METADATA
neuroslice-1.0.4.dist-info/WHEEL
neuroslice-1.0.4.dist-info/entry_points.txt
neuroslice-1.0.4.dist-info/top_level.txt
neuroslice-1.0.4.dist-info/RECORD
