Metadata-Version: 2.4
Name: neuroslice
Version: 1.0.4
Summary: Slice-wise brain tumor detection and 3D mask reconstruction from MRI
Requires-Python: >=3.8
Requires-Dist: nibabel
Requires-Dist: numpy
Requires-Dist: ultralytics
Requires-Dist: tqdm
Requires-Dist: opencv-python
Requires-Dist: huggingface-hub
